[
  {
    "name": "Robin L. Kelly",
    "address": [
      {
        "line1": "1000 E. 111th St.",
        "city": "Chicago",
        "state": "IL",
        "zip": "60628",
        "phone": "773-321-2001",
        "longitude": -87.6012886,
        "latitude": 41.6944193
      },
      {
        "line1": "304 S. Indiana Ave.",
        "line2": "lower level",
        "line3": "Kankakee City Hall",
        "city": "Kankakee",
        "state": "IL",
        "zip": "60901",
        "phone": "708-679-0078",
        "longitude": -87.861261,
        "latitude": 41.117146
      },
      {
        "line1": "600 Holiday Plaza Dr.",
        "line2": "Suite 505",
        "city": "Matteson",
        "state": "IL",
        "zip": "60443",
        "phone": "708-679-0078",
        "longitude": -87.7382453,
        "latitude": 41.5042785
      }
    ],
    "party": "Democratic",
    "phones": [
      "202-225-0773"
    ],
    "emails": [],
    "urls": [
      "https://robinkelly.house.gov"
    ],
    "photoUrl": "https://theunitedstates.io/images/congress/450x550/K000385.jpg",
    "channels": [
      {
        "type": "Twitter",
        "id": "RepRobinKelly"
      },
      {
        "type": "Facebook",
        "id": "reprobinkelly"
      },
      {
        "type": "Instagram",
        "id": "reprobinkelly"
      }
    ],
    "sources": [
      "theunitedstates.io"
    ],
    "office": {
      "name": "United States House of Representatives IL-2",
      "level": "federal"
    }
  }
]