[{"name":"Duncan Hunter","address":[{"line1":"1611 N. Magnolia Ave.","line2":"Suite 310","city":"El Cajon","state":"CA","zip":"92020","phone":"619-448-5201","longitude":-116.9614599,"latitude":32.820926},{"line1":"41000 Main St.","city":"Temecula","state":"CA","zip":"92590","phone":"951-695-5108","longitude":-117.1470449,"latitude":33.4941712}],"party":"Republican","phones":["202-225-5672"],"emails":[],"urls":["https://hunter.house.gov"],"photoUrl":"https://theunitedstates.io/images/congress/450x550/H001048.jpg","channels":[{"type":"Twitter","id":"Rep_Hunter"},{"type":"Facebook","id":"DuncanHunter"},{"type":"YouTube","id":"CongressmanHunter"}],"sources":["theunitedstates.io"],"office":{"name":"United States House of Representatives CA-50","level":"federal"}}]