[{"name":"Ted S. Yoho","address":[{"line1":"5000 NW 27th Court","line2":"Suite E","city":"Gainesville","state":"FL","zip":"32606","phone":"352-505-0838","longitude":-82.39626,"latitude":29.678553},{"line1":"35 Knight Boxx Rd.","line2":"Suite 1","city":"Orange Park","state":"FL","zip":"32065","phone":"904-276-9626","longitude":-81.7974322,"latitude":30.1208794},{"line1":"2509 Crill Ave.","line2":"Suite 200","city":"Palatka","state":"FL","zip":"32177","phone":"502-935-6934","longitude":-81.6588895,"latitude":29.6401223},{"line1":"115 SE 25th Ave","city":"Ocala","state":"FL","zip":"34471","phone":"352-390-6413","longitude":-82.1028405,"latitude":29.1849757}],"party":"Republican","phones":["202-225-5744"],"emails":[],"urls":["https://yoho.house.gov"],"photoUrl":"","channels":[{"type":"Twitter","id":"RepTedYoho"},{"type":"Facebook","id":"CongressmanTedYoho"},{"type":"YouTube","id":"RepTedYoho"}],"sources":["theunitedstates.io"],"office":{"name":"United States House of Representatives FL-3","level":"federal"}}]