[{"name":"Mike Rogers","address":[{"line1":"1129 Noble St.","line2":"# 104","city":"Anniston","state":"AL","zip":"36201","phone":"256-236-5655","longitude":-85.8294458,"latitude":33.6595488},{"line1":"701 Avenue A","line2":"Suite 300","line3":"G.W. Andrews Federal Building","city":"Opelika","state":"AL","zip":"36801","phone":"334-745-6221","longitude":-85.3772489,"latitude":32.6481909}],"party":"Republican","phones":["202-225-3261"],"emails":[],"urls":["https://mikerogers.house.gov"],"photoUrl":"","channels":[],"sources":["theunitedstates.io"]}]