[{"name":"Zoe Lofgren","address":[{"line1":"635 N. First St.","line2":"Suite B","city":"San Jose","state":"CA","zip":"95112","phone":"408-271-8700","longitude":-121.8993988,"latitude":37.3475248}],"party":"Democratic","phones":["202-225-3072"],"emails":[],"urls":["https://lofgren.house.gov"],"photoUrl":"","channels":[{"type":"Twitter","id":"RepZoeLofgren"},{"type":"Facebook","id":"zoelofgren"},{"type":"YouTube","id":"RepZoeLofgren"}],"sources":["theunitedstates.io"],"office":{"name":"United States House of Representatives CA-19","level":"federal"}}]