[{"name":"Matt Cartwright","address":[{"line1":"400 Northampton St.","line2":"Suite 307","city":"Easton","state":"PA","zip":"18042","phone":"484-546-0776","longitude":-75.2111997,"latitude":40.6908081},{"line1":"121 Progress Ave.","line2":"Suite 310","city":"Pottsville","state":"PA","zip":"17901","phone":"570-624-0140","longitude":-76.1950516,"latitude":40.6864175},{"line1":"226 Wyoming Ave.","city":"Scranton","state":"PA","zip":"18503","phone":"570-341-1050","longitude":-75.66439729999999,"latitude":41.4093981},{"line1":"20 N. Pennsylvania Ave.","line2":"Suite 201","city":"Wilkes-Barre","state":"PA","zip":"18711","phone":"570-371-0317","longitude":-75.87917089999999,"latitude":41.2441677}],"party":"Democratic","phones":["202-225-5546"],"emails":[],"urls":["https://cartwright.house.gov"],"photoUrl":"https://theunitedstates.io/images/congress/450x550/C001090.jpg","channels":[{"type":"Twitter","id":"RepCartwright"},{"type":"Facebook","id":"CongressmanMattCartwright"},{"type":"Instagram","id":"repmattcartwright"}],"sources":["theunitedstates.io"],"office":{"name":"United States House of Representatives PA-8","level":"federal"}}]