[{"name":"Robert B. Aderholt","address":[{"line1":"205 4th Ave. NE","line2":"Suite 104","city":"Cullman","state":"AL","zip":"35055","phone":"256-734-6043","longitude":-86.840631,"latitude":34.181059},{"line1":"600 Broad St.","line2":"Suite 107","city":"Gadsden","state":"AL","zip":"35901","phone":"256-546-0201","longitude":-86.006846,"latitude":34.01421000000001},{"line1":"1710 Alabama Ave.","line2":"247","line3":"Carl Elliott Building","city":"Jasper","state":"AL","zip":"35501","phone":"205-221-2310","longitude":-87.274935,"latitude":33.83438},{"line1":"1011 George Wallace Blvd.","line2":"Suite 146","city":"Tuscumbia","state":"AL","zip":"35674","phone":"256-381-3450","longitude":-87.6794142,"latitude":34.7412348}],"party":"Republican","phones":["202-225-4876"],"emails":[],"urls":["https://aderholt.house.gov"],"photoUrl":"","channels":[],"sources":["theunitedstates.io"]}]